perfect_prompt/__init__.py
perfect_prompt/__main__.py
perfect_prompt/cli.py
perfect_prompt/flux.py
perfect_prompt/fluxapi.py
perfect_prompt/pixtral.py
perfect_prompt/refine.py
perfect_prompt-0.1.0.dist-info/METADATA
perfect_prompt-0.1.0.dist-info/WHEEL
perfect_prompt-0.1.0.dist-info/entry_points.txt
perfect_prompt-0.1.0.dist-info/licenses/LICENSE
perfect_prompt-0.1.0.dist-info/RECORD
