Metadata-Version: 2.3
Name: perfect-prompt
Version: 0.1.0
Summary: Perfect your image generation prompt with a visual LLM.
Project-URL: Homepage, https://github.com/wolfmanstout/perfect-prompt
Project-URL: Changelog, https://github.com/wolfmanstout/perfect-prompt/releases
Project-URL: Issues, https://github.com/wolfmanstout/perfect-prompt/issues
Project-URL: CI, https://github.com/wolfmanstout/perfect-prompt/actions
Author: James Stout
Classifier: License :: OSI Approved :: Apache Software License
Requires-Python: >=3.11
Requires-Dist: click>=8.1.7
Requires-Dist: httpx>=0.27.2
Requires-Dist: huggingface-hub>=0.26.1
Requires-Dist: llm-gemini>=0.3
Requires-Dist: llm-mistral>=0.7
Requires-Dist: llm>=0.17.1
Requires-Dist: mistral-common[opencv]>=1.4.4
Requires-Dist: mistral-inference>=1.5.0
Requires-Dist: python-dotenv>=1.0.1
Requires-Dist: torch>=2.4.1
Requires-Dist: xformers>=0.0.28.post1
